[
  {
    "name": "Mask",
    "price": 5000,
    "stock": 10,
    "isActive": true,
    "imageUrl": "url of  mask image",
    "UserId": 1,
    "description": "Everyone can get invisibility power with this mask"
  },
  {
    "name": "Shoes",
    "price": 15000,
    "stock": 30,
    "isActive": true,
    "imageUrl": "url of shoes image",
    "UserId": 2,
    "description": "This shoes is cannot be lost"
  },
  {
    "name": "Bike",
    "price": 500000,
    "stock": 5,
    "isActive": true,
    "imageUrl": "url of bike image",
    "UserId": 3,
    "description": "This bike was completed with GPS and Bazooka"
  }
]
